{
  "scraped_at": "2026-03-22T05:31:53.317Z",
  "schools": {
    "sfu": {
      "sfuesports": {
        "post_ids": [
          "DVeuzheEvVf",
          "DV92mZSGqEG",
          "DVC8jlSkSVp",
          "DU4VdTNDxuI",
          "DTCfyhuFqFm",
          "DSLOXsUlo5-",
          "DRicco5kjUI",
          "DQqNWIgEeEq",
          "DQlJplEEQfc",
          "DQM3J2tj1xQ"
        ],
        "post_count": 10,
        "status": "partial"
      },
      "sfuartists": {
        "post_ids": [
          "DLBJljoz57l",
          "DWE4qSvDyOM",
          "DVmSAhaklgn",
          "DVmQRE8EsjL",
          "DVfgwudE3u5",
          "DVIJRUPkbef",
          "DVF0nj9ig1T",
          "DUyxU1FEyOD",
          "DUmxeqRkeDJ",
          "DUREbOKgR_j"
        ],
        "post_count": 10,
        "status": "partial"
      },
      "caseitsfu": {
        "post_ids": [
          "DWAwC0mAJRs",
          "DWAm2CxgLtq",
          "DVh6knwFsPT",
          "DVh4FiRFjIg",
          "DVh0lhfFIPs",
          "DVXSlFejztN",
          "DVWw9W4EpY2",
          "DVSTAQqj_3X",
          "DVSE0kkj_En",
          "DVK_b8JFrFU"
        ],
        "post_count": 10,
        "status": "partial"
      },
      "sfurobotics": {
        "post_ids": [
          "DAZKFBRSSTR",
          "DADK5cyxcC-"
        ],
        "post_count": 2,
        "status": "partial"
      },
      "sfuccs": {
        "post_ids": [
          "DV-C3tnFKRg",
          "DVpIfJDDzE5",
          "DBQNGJoRzaP",
          "DWHkYNeATJX",
          "DWE4mbbjwAs",
          "DWC27rsj-qR",
          "DWAAhbPEhso",
          "DV_q4p2j4hx",
          "DV_RiiVlLnd",
          "DV96119Cb-B"
        ],
        "post_count": 10,
        "status": "partial"
      },
      "awmsfu": {
        "post_ids": [
          "DVxN9-OkZyo",
          "DUQ_rjwkkfl",
          "DRxyHriEhtJ",
          "DQ0GZOnEoRf",
          "DF68KrgxdbD",
          "DCSXCZsz5y4",
          "DBSQtt7SVLw",
          "C6f7YQ2O8zm",
          "C4eNmCCv0Pk",
          "C3tRmJxy4z8"
        ],
        "post_count": 10,
        "status": "partial"
      },
      "sfufoodieclub": {
        "post_ids": [
          "DJ-TdriT9Vo",
          "DWE0ZaXlEfP",
          "DV4GCUVkpEK",
          "DVyy5DllHCa",
          "DVtsrHvFDDe",
          "DVg4ftyD72d",
          "DVg4IpSFIPU",
          "DVLTts7FPLy",
          "DUqzcuMkbx3",
          "DUlp52OFN9y"
        ],
        "post_count": 10,
        "status": "partial"
      },
      "sfurobotsoccer": {
        "post_ids": [
          "DWCT6dgj8fO",
          "DVSIVwzkoOH",
          "DUQHiZOEnsn",
          "DT_hsxJktx4",
          "DTcYYp9FNqe",
          "DTWbPi4Afun",
          "DSdWcq8EhPE",
          "DRveYePj98G",
          "DRI_5m6lMH_",
          "DQDaOMvCak7"
        ],
        "post_count": 10,
        "status": "ok"
      },
      "sfu_psa": {
        "post_ids": [
          "DK093vLu7XS",
          "DWF7TG8EuxV",
          "DVt1uxfEp0k",
          "DVRNeH8E-uH",
          "DTj3hOiDjVr",
          "DTKI78rjszG",
          "DQ7Xu_pgTZQ",
          "DQtUYwdkX8J",
          "DQLEfDHj8ZC",
          "DQBcis1jQOT"
        ],
        "post_count": 10,
        "status": "ok"
      },
      "bpksa_sfu": {
        "post_ids": [
          "DOFNlA8DxUE",
          "DWHpDSVEj2k",
          "DWHk0HiATOf",
          "DVzijmUjwLa",
          "DVt1uxfEp0k",
          "DVtu9Swjygl",
          "DVr2lfBlFJO",
          "DVeU9gogas3",
          "DVbz4OMErYq",
          "DUtzKIZEkHB"
        ],
        "post_count": 10,
        "status": "ok"
      },
      "sfuwics": {
        "post_ids": [
          "DSN_C-jEkCO",
          "CzARAqypbOH",
          "DWHYtFASLQo",
          "DWCT5Kgj7Wj",
          "DWCMuW5kj3V",
          "DV8rrvMFJ75",
          "DV60rh-kuZs",
          "DV1ZCUAj2wL",
          "DVxYtI7lCNc",
          "DVxYP2oFDma"
        ],
        "post_count": 10,
        "status": "ok"
      },
      "sfu.chess": {
        "post_ids": [
          "DFbuKV6szhw",
          "DGZaoLsMM-Z"
        ],
        "post_count": 2,
        "status": "ok"
      },
      "sfu_essu": {
        "post_ids": [
          "DWGPmzIlfxD",
          "DWAZJf1j5Kc",
          "DWAILuYkgPC",
          "DVtUp6QlY_0",
          "DVSm8IiFeG_",
          "DUd5FVlEle-",
          "DTRgu-FkZCI",
          "DTLfpGqEq0A",
          "DSwF-UAkf72",
          "DSVsDTmklI-"
        ],
        "post_count": 10,
        "status": "ok"
      },
      "sfugolfclub": {
        "post_ids": [
          "DQcNW9iASvN",
          "DWH58C6AScf",
          "DVNTFvbkQkl",
          "DUm48Z9kblY",
          "DUgwXDrkvKQ",
          "DUW2kV1gWSU",
          "DUWFOAjAe4W",
          "DUKiiXBDktF",
          "DTwIRJzEksa",
          "DTb8ZqgkZ6N"
        ],
        "post_count": 10,
        "status": "ok"
      },
      "sfuastronomyclub": {
        "post_ids": [
          "DWF7TG8EuxV",
          "DVtwMzqFNJm",
          "DVH_IzGFK9w",
          "DUWT_mygcJb",
          "DT3aeIbD1YP",
          "DTlfs9gFCLA",
          "DTbFpoQlHf1",
          "DTYg29ulKOJ",
          "DTV8JJllMVB",
          "DTTXRihlP0S"
        ],
        "post_count": 10,
        "status": "ok"
      },
      "sfulyfeclub": {
        "post_ids": [
          "DWH7xCtAYNm",
          "DV7hLLbMBm1",
          "DVwy6DIgYyB",
          "DVuitWYETKP",
          "DVmS-vrDGqi",
          "DVhywBejB5e",
          "DVf1jhaDJSg",
          "DVcE3QfEtG_",
          "DVMj80FkqC5",
          "DVLUBZajLJ9"
        ],
        "post_count": 10,
        "status": "ok"
      },
      "sussfu": {
        "post_ids": [
          "DWKMdcJEjqq",
          "DWEjMAHuy_u",
          "DWCL5OGjt46",
          "DV8xcfSFegJ",
          "DV2H7K7Eb4k",
          "DVwHQiOlfYa",
          "DVt1uxfEp0k",
          "DVevAR-kmvK",
          "DVZOFrpkk5I",
          "DVXZEwaEeoV"
        ],
        "post_count": 10,
        "status": "ok"
      },
      "sfurocketry": {
        "post_ids": [
          "DVuvPXfFNGz",
          "DUIAaQVCkAM",
          "C1Q-ZSOLwtz",
          "CzGzXWpr6t4",
          "Cy4mqmWrwqk",
          "Cye-1eurXSN",
          "Cwna3tbLlTG",
          "CwOjfdjravY",
          "CvOUEfeNae-",
          "CvLOSX3yjnu"
        ],
        "post_count": 10,
        "status": "ok"
      },
      "sfuinvest": {
        "post_ids": [
          "DU6icdukofv",
          "DUhgsD7Da7O",
          "DUcNpZsFOE4",
          "DUWOiqJkhVV",
          "DR6GJu4EYiY",
          "DRyrfunjibM",
          "DRs44byATtC",
          "DQqP_q2kQ6p",
          "DPj-JFKgX-G",
          "DPAfTGziaHH"
        ],
        "post_count": 10,
        "status": "ok"
      },
      "sfucybersecurity": {
        "post_ids": [],
        "post_count": 0,
        "status": "ok"
      },
      "sfucss": {
        "post_ids": [
          "DTwxW67Di4f",
          "DVt1uxfEp0k",
          "DVgskJ_D29s",
          "DVgrvB-FbL-",
          "DTbzNngkSfa",
          "DTby01hEee4",
          "DTLkxrikqmF",
          "DR5PAxeiTR5",
          "DQ9j-QOiTYZ",
          "DQ7Xu_pgTZQ"
        ],
        "post_count": 10,
        "status": "ok"
      },
      "sfuoutdoorsclub": {
        "post_ids": [
          "DVpchZdkU6b",
          "DVZSiF7DyiJ",
          "DU6UEAfiULH",
          "DU6T5TJiXoN",
          "DUMcq7dgQK7",
          "DUAMDFKDqqr",
          "DT-9AgND6lu",
          "DTyGnqvAX2I",
          "DTvoy-vEpnZ",
          "DRAXFZHD-2a"
        ],
        "post_count": 10,
        "status": "ok"
      },
      "sfubnss": {
        "post_ids": [
          "DVfUIvLFL0a",
          "DVPWn-yEp0C",
          "DU9pBq-kUZI",
          "DUr5GOOkY7T",
          "DUpIwMZkWwu",
          "DTjEoz5kmec",
          "DTbhYo_gcf_",
          "DTaqQTYEe9i",
          "DTS7z3RkVoS",
          "DTOumyEgTwO"
        ],
        "post_count": 10,
        "status": "ok"
      },
      "sfuaxisconsulting": {
        "post_ids": [
          "DVzcEyYEnUC",
          "DVkIkEIicjz",
          "DVjXFTPD7XQ",
          "DVhwoN4EV-Q",
          "DVe-VZWkuMK",
          "DVZ1TNBD-kr",
          "DVXZT4mEU4v",
          "DVWyzqvEgSa",
          "DVRhdhnEsrx",
          "DVNO__4kctJ"
        ],
        "post_count": 10,
        "status": "ok"
      },
      "phidesfu": {
        "post_ids": [
          "DWApXpFARTf",
          "DV87Hk9gBkI",
          "DVqzWPsSrdi",
          "DVY8B59kpPU",
          "DVXYXPBFFe3",
          "DVAxzJaFFiG",
          "DUzQ0VklGGs",
          "DUq2cmbkryq",
          "DUjQxfbEqDn",
          "DUizx1KgJQI"
        ],
        "post_count": 10,
        "status": "ok"
      },
      "mbbsu": {
        "post_ids": [
          "DV96CJmGnEC",
          "DVkBmIXjzKY",
          "DVgrvB-FbL-",
          "DVcQDfxkpsg",
          "DVITiaiAHav",
          "DVHfUqskvYD",
          "DVHjwvskpjx",
          "DUHFcBOkvuo",
          "DTwxW67Di4f",
          "DTgPT2lEqIq"
        ],
        "post_count": 10,
        "status": "ok"
      },
      "wict_sfu": {
        "post_ids": [
          "DVHaFQ4EkTj",
          "DU4ckvslC1H",
          "DUReEbsEgKr",
          "DTTjG1Lkpoi",
          "DRQe-6xgewM",
          "DRK5IQTEtWi",
          "DRIqC-Lkmct",
          "DRD8snKEZ6J",
          "DQ8HmjLkfVG",
          "DQxK2b4EhbH"
        ],
        "post_count": 10,
        "status": "ok"
      },
      "sfucycling": {
        "post_ids": [
          "DThbF6SFRHp",
          "DOr6FZ_EWGp",
          "DOaF-fnkaoX",
          "DOMK_DCDx9a",
          "C7UiIl7vGLJ",
          "C6E2lM_S99w"
        ],
        "post_count": 6,
        "status": "ok"
      },
      "eimcsfu": {
        "post_ids": [
          "DV0LM73Cjib",
          "DT1K5r7EiXF",
          "DTjHJhaEiuo",
          "DRcmKXhD9tP",
          "DQ8IqCsjIVh",
          "DQ4jUCPDzZz",
          "DQUQozzEQs-",
          "DQIrvZVkS9l",
          "DPPMWVWgUc4",
          "DOfAaoEiZzC"
        ],
        "post_count": 10,
        "status": "ok"
      },
      "sfu_sassa": {
        "post_ids": [
          "DWEv1hBE4a1",
          "DWDA5_yCfGI",
          "DVRuwRoCA5f",
          "DVRuLFyiM_t",
          "DVQpbX3iOEi",
          "DUoYtdrktxL",
          "DTq3a8AAQ6K",
          "DToxhf7iKbE",
          "DTeHIWgkoyz",
          "DSrK7S8kRi0"
        ],
        "post_count": 10,
        "status": "ok"
      },
      "sfuwstem": {
        "post_ids": [
          "DTdv6JlExSx",
          "DVo-z5HAddx",
          "DVY17UJAGLp",
          "DT8QEomDzzz",
          "DTRXyKLj7Vf",
          "DRfn7DbE195",
          "DQvIufhDywR",
          "DQkhCr4ElJh",
          "DQiMcb_gbiB",
          "DQdYUhJEVJC"
        ],
        "post_count": 10,
        "status": "ok"
      },
      "ace_sfu": {
        "post_ids": [
          "DVxcLj5Foxq",
          "DGzhFEkx-py",
          "DWIBDA4D8T6",
          "DV9kgGKEixe",
          "DVziSv2mcXq",
          "DVmJ9AZkm-l",
          "DVefK7Mkvy2",
          "DVRjZLbEqL6",
          "DVMa92VEaho",
          "DVJ3UYNFlhH"
        ],
        "post_count": 10,
        "status": "ok"
      },
      "msusfu": {
        "post_ids": [
          "DWEv1hBE4a1",
          "DV4E0jjmRja",
          "DVRNeH8E-uH",
          "DUQ_rjwkkfl",
          "DRs8_FOEQ6W",
          "DQ5W-kxkd3s",
          "DQp2rWVEj3i",
          "DQiBV8hkqKN",
          "DP2xuKfEYW7",
          "DOxSb3Ljjlg"
        ],
        "post_count": 10,
        "status": "ok"
      },
      "sfu_biology": {
        "post_ids": [
          "DWFEa10knHn",
          "DVwgcuakr1W",
          "DVhcY0TkThy",
          "DVWxB8vEkxM",
          "DVWwtbaEhyy",
          "DVWwUjpku90",
          "DVShcRkgqym",
          "DVSgqgzkcSB",
          "DVSgTzGEc5F",
          "DVPP72tkojI"
        ],
        "post_count": 10,
        "status": "ok"
      },
      "sfu.ascend": {
        "post_ids": [
          "DUtg_Q4EvFN",
          "DUyjVk5kj8D",
          "DUwhpUsD3Br",
          "DUG3htUkgtT",
          "DUB1GDAE26I",
          "DT1UgvDAWrl",
          "DTtJt5lEhgs",
          "DTlYqq3EvbD",
          "DTTkXLqErAu",
          "DTLzeepE7qq"
        ],
        "post_count": 10,
        "status": "ok"
      },
      "sfudsss": {
        "post_ids": [
          "DUi15CMgCDv",
          "DUczsZRACDi",
          "DToSFx8khgJ",
          "DTgIZwDFOfL",
          "DTcCODilCty",
          "DTTXR41FVMm",
          "DTLiqUjknc-",
          "DQejIx-EXZK",
          "DQU7LQJEii-",
          "DQU0H7RkrDi"
        ],
        "post_count": 10,
        "status": "ok"
      },
      "sfu_misa": {
        "post_ids": [
          "DVsKeeUAPCF",
          "DVnFXdcgHKu",
          "DVjmI2xlA4b",
          "DVfKSEgEhIs",
          "DVfJufnD1ft",
          "DVfAkRFkTSc",
          "DVOtyFuj9rv",
          "DUbP0MCDwTJ",
          "DUYrFDND9oT",
          "DUWGS-VER3l"
        ],
        "post_count": 10,
        "status": "ok"
      },
      "sfusurge": {
        "post_ids": [
          "DWII_ugCUWn",
          "DV_xtoYAY5c",
          "DV-AroEDQAH",
          "DV7RArDibRM",
          "DV2HwCGCfQ1",
          "DVkQSASjeG_",
          "DVhrifGDeKy",
          "DUzvY1cjcoR",
          "DUv5hUlgUxz",
          "DUhkk1cERgF"
        ],
        "post_count": 10,
        "status": "ok"
      },
      "sfu_mk": {
        "post_ids": [
          "DI4C_9UpqBk",
          "DIWnIasvRzP",
          "DCYEqtxJSIH",
          "C_mNimPP4ID",
          "C8_QeUWRQAF",
          "C5mc9URPdze",
          "Czki630rGI8",
          "Cye8iK6LNK-",
          "Cq__Vozrkzb",
          "CqMDz_xPEnf"
        ],
        "post_count": 10,
        "status": "ok"
      },
      "sfucreativewriting": {
        "post_ids": [
          "DVNFdJblCEM",
          "DTdvqcWEuzY",
          "DRbhVzvlA6C",
          "DFYhdUeTOmx",
          "C2qcojEPEMM",
          "CywXJwpSkC1",
          "CxYlZYvPXHR",
          "CeZdcXOvotc",
          "CWwK-rAhLBf",
          "CV6PSN0PR6Z"
        ],
        "post_count": 10,
        "status": "ok"
      },
      "sfufinsa": {
        "post_ids": [
          "DWH0sLngQaA",
          "DWCr1eoEjGZ",
          "DV9hkUaBGgk",
          "DVwwWutkma9",
          "DVruyAujw2D",
          "DU1bS6rlGR4",
          "DUrVyv3kpQZ",
          "DUqzgrllBb0",
          "DUcNpZsFOE4",
          "DUbyKkaEoCB"
        ],
        "post_count": 10,
        "status": "ok"
      },
      "sfubass": {
        "post_ids": [
          "DO60cM4kxej",
          "DWKMdcJEjqq",
          "DWIho6kiOV4",
          "DWCZWweD7UD",
          "DV6yU-ekuK_",
          "DV4DTH4FGy9",
          "DV1eg8EGupI",
          "DVy5tulEemN",
          "DVwS6Jfjyn9",
          "DVwHQiOlfYa"
        ],
        "post_count": 10,
        "status": "ok"
      },
      "enactussfu": {
        "post_ids": [
          "DVzABi1kjCz",
          "DWKLuzpFXZI",
          "DWHjeovmHrV",
          "DWCWh6JFaK5",
          "DV_1LO4lScB",
          "DV9QYJ4j3hC",
          "DVwYZzMEtI_",
          "DVtzjH2kliC",
          "DVrOxxuklpN",
          "DVop_mvkuYn"
        ],
        "post_count": 10,
        "status": "ok"
      },
      "sfuprelaw": {
        "post_ids": [
          "DVR2w4Nkly-",
          "DWCd1a3klWJ",
          "DV4mM7lDyle",
          "DV4l6YaD1H6",
          "DVzlqFKiVvq",
          "DVwfnxFEjR6",
          "DVwfebbEiFO",
          "DVt12hSkifM",
          "DVt1z0Sko2Z",
          "DVt1xqlkncg"
        ],
        "post_count": 10,
        "status": "ok"
      },
      "fentanilsfu": {
        "post_ids": [
          "DHpbazNxJki",
          "DCpz1Fmy_QU",
          "DByoscLvqZ0",
          "C5OidymRS9U",
          "C2dc-rqP-QO",
          "C2anGYeSHmG",
          "Cy3yj4tvFEg",
          "CyOlW0UJ8a0",
          "Cx2JESAu41y",
          "CxTe_uBPjGi"
        ],
        "post_count": 10,
        "status": "ok"
      },
      "ywibsfu": {
        "post_ids": [
          "DP9mNt2kkgU",
          "DWE9EzrD_4G",
          "DV9X_-xEoOm",
          "DVoc5iUEVLP",
          "DU_gLYkEoap",
          "DU1Sz8JEoBL",
          "DUwSZ0qku6d",
          "DUo1KArD5Tn",
          "DTt0Cu1kdS9",
          "DToPbQ0kqNw"
        ],
        "post_count": 10,
        "status": "ok"
      },
      "aiesecsfu": {
        "post_ids": [
          "BSm0audBPkK",
          "BSUel9Rhc5y",
          "BSJsqUVBnms",
          "BSB6NT7hDvf",
          "BRwTJNsB1YD",
          "BQn-19Bj06u",
          "BPjBYGcgJqU",
          "BPb274cg4Tx",
          "BPa3ln5gsl3",
          "BPYXPSGA9iR"
        ],
        "post_count": 10,
        "status": "ok"
      },
      "sfusma": {
        "post_ids": [
          "DWFaWpPD89W",
          "DV4fCUTEuMJ",
          "DV1uxkLktp9",
          "DVy9rQHkjCk",
          "DVwfVbMkhgA",
          "DVrk9sYkgk2",
          "DVj11uSkpQg",
          "DVeuao4Evz0",
          "DVZQwNpEmT-",
          "DVUOtbEkkLp"
        ],
        "post_count": 10,
        "status": "ok"
      },
      "sfu_hrsa": {
        "post_ids": [
          "DWHiTxaAe7q",
          "DVj3yKKgRB0",
          "DVedRqKkqE6",
          "DVb3ZwpkufL",
          "DVWoYx3j9BE",
          "DVUWhGvklHd",
          "DVSIQ7hD3ML",
          "DVMaBBgkihf",
          "DVJz-2iks-f",
          "DVHdDfJAX1V"
        ],
        "post_count": 10,
        "status": "ok"
      },
      "sfuasa": {
        "post_ids": [
          "DWDVQQnDXOg",
          "DVutCmBk5QV",
          "DVfSuW_kbvP",
          "DVaOucDE_wH",
          "DVW2ZD3kjil",
          "DUwM0uLD52I",
          "DUpa9tEkVLt",
          "DUjzDFWj-EG",
          "DUZf4i9j3zG",
          "DULyg8zD7Rp"
        ],
        "post_count": 10,
        "status": "ok"
      },
      "aiesecinsfu": {
        "post_ids": [
          "Cm2QYYwSx1F",
          "CmH5H6oybP_",
          "C1IN9OVSYVK",
          "CzW3005SdHD",
          "CyMSC-DyIRe",
          "CyJhY0LP3EO",
          "CyJMzt_LMiV",
          "CyG8qTmr6XR",
          "CyEX1oZRGrA",
          "Cx8qjtCv5FD"
        ],
        "post_count": 10,
        "status": "ok"
      },
      "tedxsfu": {
        "post_ids": [
          "Cz9cmy3PInf",
          "Cz4TE1xuTW3",
          "CxbggzrSBFL",
          "C2Iy-QCv4ZH",
          "Cz7dLkSvVlB",
          "Cz5DGhWOFAo",
          "CzgAFJHOtNz",
          "Cze7YgUvfy9",
          "Czefrk7xKz6",
          "Czc45FQrRK8"
        ],
        "post_count": 10,
        "status": "ok"
      },
      "sfumusic": {
        "post_ids": [
          "DPARQ-vgXwY",
          "DPZkdCmAXgN",
          "DPAU7RBgYMU",
          "DWF0bR5iadx",
          "DWC80L_j1Rq",
          "DWCRfktgM44",
          "DV9esT7Elxo",
          "DU6Vv97Ei8L",
          "DUrXcuigaXD",
          "DUoXEpfEgC2"
        ],
        "post_count": 10,
        "status": "partial"
      },
      "sfufilmstudentunion": {
        "post_ids": [
          "DMJChi1BUiN",
          "DWHcUMUCSxT",
          "DVzfWmnj7SS",
          "DVylHCFlV5d",
          "DUXfCLqjo-b",
          "DTdjPCBEqDz",
          "DRkoHP_kqgz",
          "DRkniesEs3l",
          "DRFiySzj2lo",
          "DQnBqv0EkHW"
        ],
        "post_count": 10,
        "status": "partial"
      },
      "ssss.sfu": {
        "post_ids": [
          "DV-UtbvDS9c",
          "DV0D21xDc16",
          "DU9-KmuEQce",
          "DVZLOS_EjXQ",
          "DVSNtCAEeOj",
          "DVP9-9Ykf6L",
          "DVCOvZlkq-E",
          "DUsQRBckcd8",
          "DUh1hFble-G",
          "DT_x_skDzH4"
        ],
        "post_count": 10,
        "status": "partial"
      },
      "sfu_apcs": {
        "post_ids": [
          "DTy6m71lERS",
          "DThIjzJFCqU",
          "DRFwQtTkqIj",
          "DPkyCmMkb66",
          "DI2Ua-bzdw9",
          "DC-IaXAzoSF",
          "DCC5sb0ze04",
          "DBmqGZqzKqK",
          "DBKg7OEyrRc",
          "C3EBJKkx_8f"
        ],
        "post_count": 10,
        "status": "ok"
      },
      "sfuissa": {
        "post_ids": [
          "DV1DGOvFMvn",
          "DVZTxDhEngD",
          "DUEq8bfEuBL",
          "DWE0UICgbBi",
          "DVypNWyASTY",
          "DVqv5POlAxm",
          "DVbZ_pIkrQS",
          "DVWQYdlFFXI",
          "DVRiMlnkr10",
          "DVL9RJKD359"
        ],
        "post_count": 10,
        "status": "ok"
      },
      "sfulsu": {
        "post_ids": [
          "DVw9ML2j6Sh",
          "DU6X8SFEuzJ",
          "DUmO25Xj3O1",
          "DTdrBIDkufi",
          "DS9ekeAlL9H",
          "DRfrEfeElIc",
          "DRdD_KKkueR",
          "DQr4lZXkoZE",
          "DP-BLQtj3QK",
          "DPlCg1cAE_R"
        ],
        "post_count": 10,
        "status": "ok"
      },
      "see_sfu": {
        "post_ids": [
          "DWKKsYbkmU5",
          "DWHJ8keE_sG",
          "DV1Vr64FAxh",
          "DVy_ALIktes",
          "DVy97udE0Yl",
          "DVwYKS3EqF_",
          "DVwCvDtFLua",
          "DVtoKQ6lLvA",
          "DVq8yiolPjB",
          "DVkSt1Kk9hD"
        ],
        "post_count": 10,
        "status": "ok"
      },
      "sfu.theatre": {
        "post_ids": [
          "DVFHOGDAerT",
          "DUWeVzKk6cR",
          "DWCX56Pky1w",
          "DWBjKMdEmrA",
          "DV_qHEbku34",
          "DV9SWSbEgtU",
          "DV9HY0CjqQz",
          "DV4AnsBkh2T",
          "DV1vdqHEmqI",
          "DVxMiI9FBJK"
        ],
        "post_count": 10,
        "status": "ok"
      },
      "wiesfu": {
        "post_ids": [
          "DWLFz55ANj0",
          "DVY17UJAGLp",
          "DUhTYekgJet",
          "DUZTH7pkoII",
          "DRVIWc8kvFj",
          "DRLKuTqEjsv",
          "DRGD4-7kr8e",
          "DQ8MdeykTSf",
          "DQQToRyESgA",
          "DQIKT3lkvR1"
        ],
        "post_count": 10,
        "status": "ok"
      },
      "sfudance": {
        "post_ids": [
          "DV-UHvuFexH",
          "DV4QK1mEjPc",
          "DV1PKcQinsR",
          "DVyrtKUFM0-",
          "DVwUqRBAq-r",
          "DVwF6wSlGwn",
          "DVrzMTTijbn",
          "DVrjaguknxZ",
          "DVrbUsXioVa",
          "DVjTGbuihEc"
        ],
        "post_count": 10,
        "status": "ok"
      },
      "sfu.esa": {
        "post_ids": [
          "DUKJq1flM12",
          "DT6nJg5iZI8",
          "DV9ODimgZ2N",
          "DVylKLZjX5A",
          "DVjoeEekqn5",
          "DVZVSHkEoqD",
          "DVHksxhEnwa",
          "DVAQ_djDlDc",
          "DU1iJm_kuZa",
          "DU1VhtmktBT"
        ],
        "post_count": 10,
        "status": "ok"
      },
      "theatreproduction": {
        "post_ids": [
          "DV2ExtWjwNr",
          "DVyljWQCsLo",
          "DWCX56Pky1w",
          "DV_qHEbku34",
          "DV9SWSbEgtU",
          "DV4QK1mEjPc",
          "DV4AnsBkh2T",
          "DV1PKcQinsR",
          "DVyrtKUFM0-",
          "DVwUqRBAq-r"
        ],
        "post_count": 10,
        "status": "partial"
      },
      "611studio": {
        "post_ids": [
          "DUrczYegSxk",
          "DUMEnyhkgbt",
          "DSYN8tMEjee",
          "DRiiVOcAU5S",
          "DRVDs0BEuAZ",
          "DQXiXR5kthP",
          "DP4ubLrElvm",
          "DPccZVbAbjZ",
          "DOebLM6EhEO",
          "DIPnSO6SpdQ"
        ],
        "post_count": 10,
        "status": "ok"
      },
      "scastudentunioncommons": {
        "post_ids": [
          "DGny1K7ptxH",
          "DF4Ha-MxnzJ",
          "C7pV9xlSltp",
          "C7DILS0Ph0K",
          "C6wbUhbRE5B",
          "C6P1XiZspIn",
          "C6PII-Hy14J",
          "C4ZQ6nyxtqk",
          "CzR5LaeSN8N",
          "CzCekncydZc"
        ],
        "post_count": 10,
        "status": "ok"
      }
    },
    "ubc": {
      "ubcstrings": {
        "post_ids": [
          "DO10ev_EkEF",
          "DWCK8J4ASwp",
          "DU4VKPIgXWp",
          "DUeOtsRElUN",
          "DT3Rl5hAduI",
          "DTv8Rodktg2",
          "DToSmZXEjZN",
          "DR0jhLXgb8o",
          "DRVoTuDEndm",
          "DRD1JOTkQjb"
        ],
        "post_count": 10,
        "status": "partial"
      },
      "ubclassa": {
        "post_ids": [
          "DQFSfLbEs1h",
          "DWFYN86jwIa",
          "DV9xMI6DymH",
          "DVzGSImkiUE",
          "DVtbutGFD9o",
          "DU_xE2Ukv3N",
          "DUWUCCoEkps",
          "DTgJyLmEjX3",
          "DRiWjntEl5d",
          "DQuqRxckg3Y"
        ],
        "post_count": 10,
        "status": "ok"
      },
      "eprojects": {
        "post_ids": [],
        "post_count": 0,
        "status": "ok"
      },
      "ubcmeditationcommunity": {
        "post_ids": [
          "DWC52_rD1ON",
          "DVpXgVUlFAc",
          "DVb-v1mEvwf",
          "DVFAjyREubt",
          "DUyykFUEgTF",
          "DURo_DfAWG6",
          "DT9AVMeEkxh",
          "DTZgHIQFOG6",
          "DS5rt6Tk1C0",
          "DSq0nUEAvKi"
        ],
        "post_count": 10,
        "status": "ok"
      },
      "ubcdsci": {
        "post_ids": [
          "DVy_275EiyV",
          "DWHfpZ4gZSr",
          "DWFHKMSkvyi",
          "DV_wxLwDyjY",
          "DV85dbdkQBp",
          "DV6FxfKFPIG",
          "DV4Ax_KD8AO",
          "DVr_QloAYyc",
          "DVoxu0-Eq2u",
          "DVeaz9Zkpmo"
        ],
        "post_count": 10,
        "status": "ok"
      },
      "ubcfa": {
        "post_ids": [
          "DVwNPdQCSjs",
          "DUQoGRxj5GB",
          "DSFlQPJDbN2",
          "DWHNRgOFUlV",
          "DWG926DGMqC",
          "DWFW6qIjYwf",
          "DWEZJL-DG40",
          "DWCSIUvDppH",
          "DWB0QGcjwQk",
          "DV_4pOKgaMN"
        ],
        "post_count": 10,
        "status": "ok"
      },
      "ubcuxhub": {
        "post_ids": [
          "DV_w0Q5D8pk",
          "DV9eVqykg60",
          "DV4dJPLErkB",
          "DVnLNY1Fv-Q",
          "DVZ8JtyiepR",
          "DU9e92MAfnb",
          "DU66usiASJH",
          "DUJU4tHEqt3",
          "DTdpaGuEtOD",
          "DTbxd72EV46"
        ],
        "post_count": 10,
        "status": "ok"
      },
      "ubcvseus": {
        "post_ids": [],
        "post_count": 0,
        "status": "ok"
      },
      "ubcmus": {
        "post_ids": [
          "DTtGTf2EpSQ",
          "DQ6AE1ZkTRF",
          "DQIi5ucEYOw",
          "DOT00k_ETey",
          "DNCeSy5xPXY",
          "DMtcZ1yyRnw",
          "DLlOX85hG1q",
          "DKdSzLNyyjz",
          "DJcU_WxSMll",
          "DIeyZabzn2t"
        ],
        "post_count": 10,
        "status": "ok"
      },
      "ubcengineers": {
        "post_ids": [
          "DWHRYvEEZZz",
          "DWEf0eLlaYU",
          "DV7CJCRAUHq",
          "DV4YAZDEuzh",
          "DV2F8kbj2UM",
          "DV14-nlAfaX",
          "DVzsJhlFFcB",
          "DVzeQXbD9kD",
          "DVwg37Skju0",
          "DVrl49elKG6"
        ],
        "post_count": 10,
        "status": "ok"
      },
      "ubctradinggroup": {
        "post_ids": [
          "DPpDm1aEtZ9",
          "DVwjYx8EvmG",
          "DVtmQgKmHWm",
          "DVgmMKNFIUz",
          "DVcvm0jjtJA",
          "DVZ-IwFjAb4",
          "DVH7gaNjB4I",
          "DU81XJ4knn5",
          "DT5im7hDoDP",
          "DSQgyWCE6EW"
        ],
        "post_count": 10,
        "status": "ok"
      },
      "ubcstartups": {
        "post_ids": [
          "DUjV3GnEu1f",
          "DVMYfCDkp8K",
          "DUsIPORlG9v",
          "DWIRc0AFEPu",
          "DWDmRHTCjI4",
          "DV69CiokloW",
          "DV2IhATitmz",
          "DVz1CqTCiQU",
          "DVrdHGmEtSO",
          "DVmjr4vgXDu"
        ],
        "post_count": 10,
        "status": "ok"
      },
      "ubcfencing": {
        "post_ids": [
          "DVVNY3LFbma",
          "DAEoeSqy3ES",
          "DWHRfd6lG7j",
          "DV9UyhOknyw",
          "DTE7sHCFZ0F",
          "DSrdeYjFcov",
          "DRS7Qr-EquJ",
          "DQxryCVj7cy",
          "DPFcqEHAVCn",
          "DOkObJ1kTo8"
        ],
        "post_count": 10,
        "status": "ok"
      },
      "ubcaccounting": {
        "post_ids": [
          "DWHpcBFks3C",
          "DV_4X_sgQQb",
          "DV4NyOOkn8S",
          "DVof2sLD2h-",
          "DVeDzfBEYt_",
          "DVbxrorEjw8",
          "DVXHnoLASk2",
          "DVHPxCtklvB",
          "DVDWAK1FfsL",
          "DU_sXrhEqR2"
        ],
        "post_count": 10,
        "status": "ok"
      },
      "tedxubc": {
        "post_ids": [
          "DRV8bTOkacv",
          "DVq-W5UgMKi",
          "DVpERI1gQv8",
          "DVoaJiHj5on",
          "DVoYbcAAAlm",
          "DVoIPzDFK9y",
          "DVm204WERjy",
          "DVm1M2BkfPo",
          "DVmXHEYkpcT",
          "DVmSqo-kmAZ"
        ],
        "post_count": 10,
        "status": "ok"
      },
      "agoracafeubc": {
        "post_ids": [
          "DVuZGv-j7eb",
          "DNhUw4UxX_e",
          "DWCJ_A6lAmI",
          "DV9wAJND2Nh",
          "DV6xExPEnsW",
          "DV38ulaD3g2",
          "DV1soZ-Evc2",
          "DV1VUIcFPxx",
          "DVzi8EZD_Dc",
          "DVwHBaDD1tG"
        ],
        "post_count": 10,
        "status": "ok"
      },
      "ubcaus": {
        "post_ids": [
          "DV12BRWkoyN",
          "DVwrQ3pEi5n",
          "DWDTiFulB_3",
          "DWHiLDoAY1k",
          "DWE5ha0AbUK",
          "DWDGV-yDzdh",
          "DV_zY59AbeR",
          "DV9wBo4AQBg",
          "DV9MXb9lMhC",
          "DV6oKYNgXVn"
        ],
        "post_count": 10,
        "status": "ok"
      },
      "pp.council.ubc": {
        "post_ids": [
          "DWKGSWWAUAN",
          "DV_5VpUEhab",
          "DV_OzGBAhvm",
          "DV9xqjBD92A",
          "DV7Sx_-Cc2T",
          "DV6-dWKktWV",
          "DV4nB_iD4hl",
          "DV4gyUCAT6S",
          "DV2Y78NkQ4p",
          "DV1R5oSArrT"
        ],
        "post_count": 10,
        "status": "ok"
      },
      "motionubc": {
        "post_ids": [
          "DPNmbGBDj11",
          "DGPszCARclf",
          "DAzYHQryvfe",
          "DAcAxAoS_Is",
          "DAVBI--ppXs"
        ],
        "post_count": 5,
        "status": "ok"
      },
      "ubc_csss": {
        "post_ids": [
          "DV9E0O2mpPS",
          "DWKkKUtErhL",
          "DWFwfublkeV",
          "DWCOLaAjcmi",
          "DV_lp0uIM4g",
          "DV66VnOEvmm",
          "DV6xhHQEqDF",
          "DVuLkF7AQSD",
          "DVgvEL-kpKQ",
          "DVeONcvlXU2"
        ],
        "post_count": 10,
        "status": "ok"
      },
      "susubc": {
        "post_ids": [
          "DWKmMmTgZzK",
          "DWId6gdBCMo",
          "DWIB6ZSgVRM",
          "DWFd7AXD9Dq",
          "DWAZGE8Gn62",
          "DV42n_WAGyx",
          "DV2BgOrAfRP",
          "DV1R5IUlDeN",
          "DVxBiUDgKXX",
          "DVuqaSRES6D"
        ],
        "post_count": 10,
        "status": "ok"
      },
      "ubcrocket": {
        "post_ids": [
          "DUovJWWEo8Q",
          "DV9ik_oEgw3",
          "DUjOp9UkqQf",
          "DUjOdXqElFr",
          "DUjON2hEswJ",
          "DUjNy7JElRk",
          "DUbdusNkhTA",
          "DUbdXC6Ep30",
          "DUWUHfwkoq6",
          "DUWTvGHEhnm"
        ],
        "post_count": 10,
        "status": "ok"
      },
      "ubcbiztech": {
        "post_ids": [
          "DWKcR0EkuX_",
          "DWE6X4dj8cy",
          "DWCJnT8lMtt",
          "DV9KhbLj42n",
          "DV4KqUDEoW4",
          "DVy9T6CEnnS",
          "DVwqg-mEmOW",
          "DVonPemj80d",
          "DVjdBXDD3Cf",
          "DVeSukgEs4L"
        ],
        "post_count": 10,
        "status": "ok"
      },
      "ubcphus": {
        "post_ids": [
          "DVY1rRgEaxW",
          "DV9HJuzAOTI",
          "DVrgX_3EvOV",
          "DVrMFC4EsEQ",
          "DVk0FUSgLJG",
          "DVSOfkEkde8",
          "DVHkApkkqAy",
          "DU9Xz54EhW4",
          "DU1VuNTkriC",
          "DUhpzRGES5j"
        ],
        "post_count": 10,
        "status": "ok"
      },
      "cookingclububc": {
        "post_ids": [
          "DV6sF0qgYEt",
          "DV1xtUqEt0B",
          "DVuo5uDEdxB",
          "DVrbgwDkm9N",
          "DVKyMW0kTpw",
          "DUmzfRikQfF",
          "DUchz3qlG9G",
          "DUY40FxkrYV",
          "DUFUYdpkeo8",
          "DTg7ajtkX-1"
        ],
        "post_count": 10,
        "status": "ok"
      },
      "ubcaiclub": {
        "post_ids": [
          "DRQlsFmjx61",
          "DRQldPiD5RA",
          "DRLYs53ga-P",
          "DRDBgLIkhn3",
          "DQcyzWfEmwc",
          "DPiDP9cEYuN",
          "DOjqVZoEo7g",
          "DOFLp1_D9_D",
          "DNbjirjyxVg",
          "DHfPqFVu7RW"
        ],
        "post_count": 10,
        "status": "ok"
      },
      "ubcma": {
        "post_ids": [
          "DVw0W-wgfZa",
          "DWKIsFpAVGw",
          "DWFEvHgktnV",
          "DWCyjqSAZL_",
          "DWAC01KEmcv",
          "DV7g598ke9a",
          "DVXPcGqAUmh",
          "DVWylsukgzK",
          "DVUyHINETft",
          "DVSIQ6NGJl3"
        ],
        "post_count": 10,
        "status": "ok"
      },
      "ubcgss": {
        "post_ids": [
          "DWE7U-GGjlu",
          "DVq9vAWFNVi",
          "DV_kGFXEoD7",
          "DWHLkUXlCBT",
          "DWFJCiwDfJp",
          "DWCI2V-Fd5X",
          "DV__dMqFL7Q",
          "DV8_VHcjtVa",
          "DVzmTnjmVTC",
          "DVwHOL6Fa9L"
        ],
        "post_count": 10,
        "status": "ok"
      },
      "ubcsprouts": {
        "post_ids": [
          "DAOrvwtyf29",
          "ClW8b7vgGZs",
          "DWFBlKdgeWN",
          "DWCziwUAfZv",
          "DV4nB5Fj4lg",
          "DVpvksrFMNE",
          "DVfHaBniPjR",
          "DVckzNIkWD6",
          "DVcKCtoErSm",
          "DVFSuCeCm4x"
        ],
        "post_count": 10,
        "status": "ok"
      },
      "ubc.cvc": {
        "post_ids": [
          "DV_x0VlARlM",
          "DWKeP1oAenN",
          "DWE02ALGZ3f",
          "DWE0csUAOjw",
          "DV9NBuFgagy",
          "DVw8hfejzLk",
          "DVroYLFgWFt",
          "DVjsfXPkuUm",
          "DVcGaiUErM_",
          "DVaIN45lF8M"
        ],
        "post_count": 10,
        "status": "ok"
      },
      "ubcconsultingclub": {
        "post_ids": [
          "eD3GJBtqTH"
        ],
        "post_count": 1,
        "status": "ok"
      },
      "bolt.ubc": {
        "post_ids": [
          "DVzi9Jtj3Fh",
          "DVcodLGka7c",
          "DVUHQegkjkS",
          "DWHyNfzEgCt",
          "DWHc4cUj1an",
          "DV4DqYDD1d6",
          "DV13RDnEk42",
          "DVxdZb0iIhl",
          "DVt5nqMErw2",
          "DVm82M-EesY"
        ],
        "post_count": 10,
        "status": "ok"
      },
      "ubcfus": {
        "post_ids": [
          "DVpnt5glbJm",
          "DV9xLMXD87g",
          "DV9kizvAYXX",
          "DVzt9QRlJvu",
          "DVtzMAlAaEa",
          "DVrGTlJGQYZ",
          "DVZf90OEl8-",
          "DVY9v5xD_iq",
          "DUwBg7fkuC3",
          "DUUmU8ZkQYR"
        ],
        "post_count": 10,
        "status": "ok"
      },
      "ubcengineering": {
        "post_ids": [
          "DTeUM2cDJQQ",
          "DO6ZI7hDw3o",
          "DPer3khATQo",
          "DWE7FhfGiHE",
          "DV_0VjdjI3M",
          "DV92mzElGZO",
          "DV2BEa5Db_M",
          "DVoOoXnEv-F",
          "DVjybSRASVa",
          "DVjPLCBkQEA"
        ],
        "post_count": 10,
        "status": "ok"
      },
      "ubcdebate": {
        "post_ids": [
          "DUEx_MSgfa8",
          "DRc2Bhukp0b",
          "DRI7HTbkeJq",
          "DQTDMnQEQgv",
          "DPRmXsMD4X-",
          "DO6i06OEvHF",
          "DO6hhFpEi7C",
          "DOtkIofkUPl",
          "DOW6KOxkkHM",
          "DOO0cYoEpL7"
        ],
        "post_count": 10,
        "status": "ok"
      },
      "ubcnus": {
        "post_ids": [
          "DHIShzNOZAW",
          "DWAmrrdDTHb",
          "DV90HJpjy3G",
          "DVkDI9Qj4cC",
          "DVhd86Xj-g9",
          "DVRd55tkjy8",
          "DVFe1HLkSEb",
          "DUrc19DgafL",
          "DURR6J9Ejsv",
          "DT8zPeokmCr"
        ],
        "post_count": 10,
        "status": "ok"
      },
      "ubclaunchpad": {
        "post_ids": [
          "DUG6GcikqMn",
          "DUAIhG-Ef77",
          "DTbOcEnEhMk",
          "DR8Wbb7j2qc",
          "DR0DkeSkVWr",
          "DRgYO-WEasG",
          "DROV45Ekbv2",
          "DQdFQJ4iaLj",
          "DPHbh_6D9mv",
          "DPFpE2nj7bn"
        ],
        "post_count": 10,
        "status": "ok"
      },
      "ubclss": {
        "post_ids": [
          "DVy213GAVYa",
          "DVt1452ksbw",
          "DVr-GUpFFVo",
          "DVr93WQlAN4",
          "DVr9huxFP0p",
          "DVebXrXEiAn",
          "DUjmPq3AUb8",
          "DUjmHLXgff2",
          "DUbP4JFAbKc",
          "DT_R7nnkx_P"
        ],
        "post_count": 10,
        "status": "ok"
      },
      "innovationonboard": {
        "post_ids": [
          "CLxYzCOsQzB",
          "CLrx7ZEMQlB",
          "CLnJ_mIMiEz",
          "CLNVYVSscO6",
          "CKsApvLswxE",
          "CKmtja6s7pw",
          "CJ7RHn0MK2o",
          "CJ7GdFdsTO_",
          "CHYhBX8AJXB",
          "CGvalElgVMU"
        ],
        "post_count": 10,
        "status": "ok"
      },
      "ubcprelaw": {
        "post_ids": [
          "DV63cP0kk2C",
          "DOG9koSj2yz",
          "DT6sGwgEfN9",
          "DWKdDRIEtLL",
          "DWCWhZmicqK",
          "DWAmoNhih1f",
          "DV2XzvACqtB",
          "DVpMS0Pj1Pv",
          "DU63E10GAjA",
          "DU4Pt36jy91"
        ],
        "post_count": 10,
        "status": "ok"
      },
      "ubcplayersclub": {
        "post_ids": [
          "DWKYYI1kpbp",
          "DWJ_0WPgcgd",
          "DWHa9FWgQwL",
          "DWFjfz5GvxZ",
          "DWDGbHdkeem",
          "DV_4mVHEnT3",
          "DV-W6SRFQbT",
          "DV7l8KDDgJ3",
          "DV48Ey-kVq5",
          "DV1xYqJEgWz"
        ],
        "post_count": 10,
        "status": "ok"
      },
      "rootsontheroof": {
        "post_ids": [
          "DUOimw0EknJ",
          "DBzSoCuT0Bu",
          "DWFNUbAEstv",
          "DV1avh-GpZI",
          "DVwXqs6Ad7m",
          "DVhRFB8EnaX",
          "DVEQkzUjdvJ",
          "DUbu7XTEv7R",
          "DTqtZ37Ejr5",
          "DTqsueuknRf"
        ],
        "post_count": 10,
        "status": "ok"
      },
      "nwplusubc": {
        "post_ids": [
          "DWGA7pKElJg",
          "DVxpBXgEtfy",
          "DVlx3BflE0L",
          "DVlvJgtlIHw",
          "DViAL84lGLg",
          "DVh9vFhEpev",
          "DVX1tbxkkRv",
          "DVSYmnpEpHN",
          "DVH4lLZFJke",
          "DVFyA2lFGm2"
        ],
        "post_count": 10,
        "status": "ok"
      },
      "ubcsmcc": {
        "post_ids": [
          "DWDGZ-hgp2h",
          "DWAHfptErgD",
          "DV9ulaeD7s2",
          "DV4svR7D-8L",
          "DVzy-eGFG2u",
          "DVu-B8egswF",
          "DVkHzlMgtWT",
          "DUepg-hjJlG",
          "DUbyG54EjvV",
          "DUT0d3xkvU-"
        ],
        "post_count": 10,
        "status": "ok"
      },
      "bestbuddiesubc": {
        "post_ids": [
          "DQdaQhBjl_g",
          "DFeyYTfxFG4",
          "DFXUBFvRifV",
          "DWJ2n-4j1Qn",
          "DVkkcgOkbws",
          "DVc2xj3jt6O",
          "DVFnzZKjgTD",
          "DUoqgV3EoLI",
          "DUTdcClCfaQ",
          "DUFnzslFQmIIZ8v1KeO-zcTcGjffuGkjYamrME0"
        ],
        "post_count": 10,
        "status": "ok"
      },
      "ubcsos": {
        "post_ids": [
          "Cb8AleEJU_E",
          "CbiWl4hJPzr",
          "Cbdsk6jlBhh",
          "CbYWdMEPZ1D",
          "CbByyEuL9yV",
          "CaVuKfHv5HV",
          "CZhyGhivgDQ",
          "CY5adVQLt0C",
          "CU8T8THhrYo",
          "CUlQEdjP0sW"
        ],
        "post_count": 10,
        "status": "ok"
      },
      "ubcwics": {
        "post_ids": [
          "DWINm7EESPK",
          "DWH0XT1EkYB",
          "DWFjKWYCeCw",
          "DWDPo1tCv3T",
          "DWCIvwHlREr",
          "DV9RAAykpti",
          "DV609HMEoIJ",
          "DVw7Zf5j9lU",
          "DVhyYJ4ESoR",
          "DVfRGsxkYnB"
        ],
        "post_count": 10,
        "status": "ok"
      },
      "ubcpmc": {
        "post_ids": [
          "DUo7BJLkQ-V",
          "DV-T7IwCThU",
          "DV5aLAXDhNL",
          "DV3uRudDlBB",
          "DVpkuDPjjG2",
          "DVWbvwEEd2m",
          "DVKPmN9Ee5-",
          "DU9CvQsEu57",
          "DU4VNxGAbzh",
          "DUuHZUijkpe"
        ],
        "post_count": 10,
        "status": "ok"
      },
      "eprojectsubc": {
        "post_ids": [
          "DV9xplwD_CZ",
          "DWK4mcMFFct",
          "DV5Yx8ujA6v",
          "DV2hD9wjA3q",
          "DVywSrfDEpw",
          "DVufbxrDCdd",
          "DVt8in3kirm",
          "DVhzdvLDCFp",
          "DVcaLKxj-Np",
          "DVHJmhSkmit"
        ],
        "post_count": 10,
        "status": "ok"
      },
      "ubcabc": {
        "post_ids": [
          "BSEmVyAlEOB",
          "BRefC5VFD0M",
          "BReeyh5luO9",
          "BRdyCUHFQLp",
          "BRMWwelBuSw",
          "BQ-_hYNlTqV",
          "BQj7Ll-jNJu",
          "BQD2N--DwnE",
          "BQB5FiMD8gZ",
          "BP-4Zs6Doq9"
        ],
        "post_count": 10,
        "status": "ok"
      }
    }
  },
  "total_accounts": 116,
  "total_posts": 1096,
  "skipped_posts": 112
}